TorchClassifierData/__init__.py
TorchClassifierData/main.py
TorchClassifierData-0.0.1.dist-info/METADATA
TorchClassifierData-0.0.1.dist-info/WHEEL
TorchClassifierData-0.0.1.dist-info/top_level.txt
TorchClassifierData-0.0.1.dist-info/RECORD
