Metadata-Version: 2.1
Name: TorchClassifierData
Version: 0.0.1
Summary: Small pytorch utility to Import,Split,Normalize and Visualize custom dataset for classification tasks
Home-page: https://github.com/shellordie/TorchClassifierData
Author: charles TCHANAKE
Author-email: shellordie@gmail.com
Keywords: Computer-vision,pytorch,preprocessing,Images,Dataset,TorchClassifierData
Classifier: Development Status :: 3 - Alpha
Classifier: Programming Language :: Python :: 3
Classifier: Operating System :: MacOS :: MacOS X
Classifier: Operating System :: Microsoft :: Windows
Requires-Dist: numpy
Requires-Dist: opencv-python
Requires-Dist: matplotlib
Requires-Dist: pandas
Requires-Dist: torch
